.DS_Store
lexer/__init__.py
lexer/version.py
lexer/api/__init__.py
lexer/api/lexer_context.py
lexer/artifact/__init__.py
lexer/artifact/lexer_artifact.py
lexer/artifact/lexer_artifact_manager.py
lexer/base/__init__.py
lexer/base/benchmark.py
lexer/base/checker.py
lexer/base/export.py
lexer/base/loader.py
lexer/configs/.lexer_config.toml
lexer/configs/__init__.py
lexer/configs/config.py
lexer/configs/loader.py
lexer/decorators/__init__.py
lexer/decorators/lexer.py
lexer/infra/__init__.py
lexer/metrics/__init__.py
lexer/metrics/latency.py
lexer/metrics/metrics.py
lexer/onnx/__init__.py
lexer/onnx/benchmark.py
lexer/onnx/checker.py
lexer/onnx/loader.py
lexer/onnx/runtime.py
lexer/output/__init__.py
lexer/output/output.py
lexer/pytorch/__init__.py
lexer/pytorch/benchmark.py
lexer/pytorch/export.py
lexer/scripts/__init__.py
lexer/tensorflow/__init__.py
lexer/utils/__init__.py
lexer/utils/benchmark_results.py
lexer/utils/csv_utils.py
lexer/utils/devices.py
lexer/utils/engines.py
lexer/utils/numpy.py
lexer/validation/__init__.py
lexer/validation/validation.py
lexer_sdk-0.0.2.dist-info/METADATA
lexer_sdk-0.0.2.dist-info/WHEEL
lexer_sdk-0.0.2.dist-info/top_level.txt
lexer_sdk-0.0.2.dist-info/RECORD
