Metadata-Version: 2.1
Name: lexer-sdk
Version: 0.0.2
Summary: Lexer Python SDK
Home-page: https://lexer.ai
Author: Lexer engineering team
Author-email: zheng@lexer.ai
Project-URL: Homepage, https://lexer.ai
Project-URL: API Documentation, https://docs.lexer.ai/docs
Keywords: artificial intelligence,pytorch,tensorflow,onnx,development,debugging,benchmarking,profiling,profiler
Classifier: Development Status :: 3 - Alpha
Classifier: Intended Audience :: Developers
Classifier: Intended Audience :: Science/Research
Classifier: Topic :: Scientific/Engineering :: Artificial Intelligence
Classifier: Topic :: Software Development :: Build Tools
Classifier: Topic :: Software Development :: Compilers
Classifier: Topic :: Software Development :: Debuggers
Classifier: License :: OSI Approved :: Apache Software License
Classifier: Programming Language :: Python :: 3
Classifier: Programming Language :: Python :: 3.7
Classifier: Programming Language :: Python :: 3.8
Classifier: Programming Language :: Python :: 3.9
Classifier: Programming Language :: Python :: 3.10
Classifier: Programming Language :: Python :: 3 :: Only
Requires-Python: >=3.7, <4
Requires-Dist: black (==22.3.0)
Requires-Dist: click (==8.1.3)
Requires-Dist: colorama (==0.4.6)
Requires-Dist: flake8 (==6.0.0)
Requires-Dist: isort (==5.10.1)
Requires-Dist: mypy (==0.950)
Requires-Dist: numpy (==1.23.0)
Requires-Dist: onnx (==1.13.0)
Requires-Dist: onnxruntime (==1.13.1)
Requires-Dist: pydantic (==1.10.4)
Requires-Dist: tf2onnx (==1.13.0)
Requires-Dist: tomlkit (==0.11.6)
Requires-Dist: torch (==1.13.1)
Requires-Dist: torchaudio (==0.13.1)
Requires-Dist: torchvision (==0.14.1)
